llmsuite/.DS_Store
llmsuite/__init__.py
llmsuite/cli.py
llmsuite/llm.py
llmsuite/prompts.py
llmsuite/settings.py
llmsuite/utils.py
llm_suite-0.2.1.dist-info/WHEEL
llm_suite-0.2.1.dist-info/entry_points.txt
llm_suite-0.2.1.dist-info/METADATA
llm_suite-0.2.1.dist-info/RECORD
