Metadata-Version: 2.3
Name: llm-suite
Version: 0.2.1
Summary: Universal tools for prompt engineering and LLM interactions.
Author: Marek Piotr Mysior
Classifier: Programming Language :: Python :: 3
Classifier: License :: OSI Approved :: MIT License
Classifier: Operating System :: OS Independent
Requires-Dist: anthropic>=0.50.0
Requires-Dist: click>=8.1.8
Requires-Dist: instructor>=1.7.9
Requires-Dist: jinja2>=3.1.6
Requires-Dist: openai>=1.77.0
Requires-Dist: pillow>=11.2.1
Requires-Dist: pydantic>=2.11.4
Requires-Dist: pydantic-settings>=2.9.1
Requires-Dist: python-dotenv>=1.1.0
Requires-Dist: python-frontmatter>=1.1.0
Requires-Python: >=3.12, <4.0
Project-URL: Homepage, https://github.com/mmysior/llm-suite
Project-URL: Issues, https://github.com/mmysior/llm-suite/issues
